<Gestures>
	<Gesture Name="shake">
		<Stroke>
			<Point X = "0.107" Y = "0.194" Z = "0.046" T = "1325480497733" alpha = "-0.35" beta = "-0.49" gamma = "-0.42" />
			<Point X = "-0.023" Y = "-0.021" Z = "-0.12" T = "1325480497763" alpha = "-2.17" beta = "-0.14" gamma = "-0.14" />
			<Point X = "-0.034" Y = "-0.084" Z = "-0.068" T = "1325480497799" alpha = "0.56" beta = "-0.63" gamma = "0.07" />
			<Point X = "-0.069" Y = "-0.191" Z = "0.026" T = "1325480497852" alpha = "0.49" beta = "-0.35" gamma = "0.91" />
			<Point X = "-0.03" Y = "0.01" Z = "0.145" T = "1325480497888" alpha = "-1.12" beta = "-0.56" gamma = "1.68" />
			<Point X = "0.029" Y = "-0.35" Z = "-0.081" T = "1325480497921" alpha = "4.55" beta = "-0.21" gamma = "0.84" />
			<Point X = "-0.015" Y = "0.233" Z = "-0.082" T = "1325480497959" alpha = "7.91" beta = "1.89" gamma = "-0.07" />
			<Point X = "-0.022" Y = "0.466" Z = "0.019" T = "1325480498005" alpha = "-0.35" beta = "3.15" gamma = "-0.07" />
			<Point X = "-0.034" Y = "0.038" Z = "0.026" T = "1325480498049" alpha = "1.33" beta = "3.5" gamma = "1.68" />
			<Point X = "0.005" Y = "-0.025" Z = "-0.008" T = "1325480498079" alpha = "14.91" beta = "2.31" gamma = "4.69" />
			<Point X = "-0.069" Y = "0.456" Z = "0.448" T = "1325480498126" alpha = "8.61" beta = "1.05" gamma = "5.11" />
			<Point X = "-0.053" Y = "-0.188" Z = "0.349" T = "1325480498168" alpha = "-11.34" beta = "-1.05" gamma = "2.52" />
			<Point X = "0.025" Y = "-0.382" Z = "-0.062" T = "1325480498201" alpha = "-3.01" beta = "-4.55" gamma = "-0.42" />
			<Point X = "0.046" Y = "0.06" Z = "-0.113" T = "1325480498240" alpha = "1.4" beta = "-5.6" gamma = "-1.61" />
			<Point X = "0.056" Y = "0.176" Z = "-0.306" T = "1325480498284" alpha = "1.33" beta = "-5.46" gamma = "-0.77" />
			<Point X = "0.083" Y = "0.344" Z = "-0.375" T = "1325480498321" alpha = "3.01" beta = "-3.71" gamma = "3.01" />
			<Point X = "0.025" Y = "0.164" Z = "-0.241" T = "1325480498363" alpha = "-0.63" beta = "-0.35" gamma = "5.39" />
			<Point X = "-0.107" Y = "0.041" Z = "-0.112" T = "1325480498402" alpha = "-2.17" beta = "3.15" gamma = "8.12" />
			<Point X = "-0.085" Y = "-0.088" Z = "-0.086" T = "1325480498449" alpha = "3.64" beta = "4.27" gamma = "10.15" />
			<Point X = "0.073" Y = "-0.321" Z = "0.084" T = "1325480498490" alpha = "-1.47" beta = "5.95" gamma = "11.69" />
			<Point X = "0.535" Y = "-1.466" Z = "0.142" T = "1325480498523" alpha = "-4.97" beta = "3.92" gamma = "8.61" />
			<Point X = "0.61" Y = "-2.536" Z = "-0.361" T = "1325480498561" alpha = "-4.13" beta = "1.82" gamma = "2.24" />
			<Point X = "-0.35" Y = "-3.748" Z = "-1.081" T = "1325480498607" alpha = "6.3" beta = "9.87" gamma = "-35.7" />
			<Point X = "-1.023" Y = "1.579" Z = "0.879" T = "1325480498643" alpha = "-13.58" beta = "9.52" gamma = "-74.97" />
			<Point X = "-0.767" Y = "5.241" Z = "1.526" T = "1325480498684" alpha = "-10.85" beta = "7.91" gamma = "-66.36" />
			<Point X = "-0.441" Y = "6.901" Z = "1.116" T = "1325480498734" alpha = "19.04" beta = "-10.64" gamma = "10.5" />
			<Point X = "-0.51" Y = "4.491" Z = "0.033" T = "1325480498757" alpha = "31.36" beta = "-19.95" gamma = "84.77" />
			<Point X = "-0.525" Y = "0.138" Z = "-0.259" T = "1325480498808" alpha = "45.92" beta = "-14.49" gamma = "116.97" />
			<Point X = "-0.184" Y = "-3.194" Z = "-0.196" T = "1325480498843" alpha = "40.74" beta = "-2.38" gamma = "114.59" />
			<Point X = "1.093" Y = "-8.939" Z = "-0.269" T = "1325480498880" alpha = "30.45" beta = "6.72" gamma = "78.82" />
			<Point X = "0.449" Y = "-9.739" Z = "-0.815" T = "1325480498920" alpha = "15.47" beta = "-0.49" gamma = "-2.38" />
			<Point X = "-0.511" Y = "-2.531" Z = "-0.757" T = "1325480498959" alpha = "-17.36" beta = "-0.7" gamma = "-101.99" />
			<Point X = "-0.275" Y = "2.56" Z = "0.769" T = "1325480499001" alpha = "-88.06" beta = "10.71" gamma = "-166.6" />
			<Point X = "-1.059" Y = "7.814" Z = "1.478" T = "1325480499041" alpha = "-36.96" beta = "7.84" gamma = "-114.59" />
			<Point X = "-0.588" Y = "10.064" Z = "0.591" T = "1325480499080" alpha = "8.19" beta = "-26.18" gamma = "16.31" />
			<Point X = "0.023" Y = "4.56" Z = "-1.039" T = "1325480499118" alpha = "10.99" beta = "-31.64" gamma = "89.32" />
			<Point X = "-0.14" Y = "-0.079" Z = "-0.711" T = "1325480499159" alpha = "37.38" beta = "-10.43" gamma = "114.52" />
			<Point X = "0.374" Y = "-3.27" Z = "-0.086" T = "1325480499206" alpha = "40.25" beta = "14.98" gamma = "106.61" />
			<Point X = "0.829" Y = "-6.846" Z = "-0.054" T = "1325480499241" alpha = "34.93" beta = "20.02" gamma = "81.76" />
			<Point X = "0.715" Y = "-8.528" Z = "-0.353" T = "1325480499280" alpha = "40.04" beta = "5.6" gamma = "19.39" />
			<Point X = "0.335" Y = "-3.748" Z = "-0.527" T = "1325480499327" alpha = "-0.98" beta = "-3.57" gamma = "-60.2" />
			<Point X = "0.212" Y = "0.183" Z = "-0.317" T = "1325480499364" alpha = "-67.55" beta = "4.34" gamma = "-130.69" />
			<Point X = "-0.343" Y = "2.522" Z = "0.2" T = "1325480499401" alpha = "-51.59" beta = "21.28" gamma = "-137.83" />
			<Point X = "-0.305" Y = "5.195" Z = "0.702" T = "1325480499448" alpha = "-44.59" beta = "18.97" gamma = "-107.94" />
			<Point X = "-0.382" Y = "5.207" Z = "1.008" T = "1325480499481" alpha = "-26.39" beta = "2.59" gamma = "-47.32" />
			<Point X = "-0.304" Y = "2.604" Z = "0.588" T = "1325480499523" alpha = "-20.72" beta = "-5.67" gamma = "-5.95" />
			<Point X = "-0.277" Y = "0.375" Z = "0.275" T = "1325480499560" alpha = "-5.74" beta = "-5.04" gamma = "13.37" />
			<Point X = "-0.281" Y = "-0.364" Z = "-0.002" T = "1325480499603" alpha = "6.23" beta = "-2.8" gamma = "21.91" />
			<Point X = "-0.217" Y = "-0.722" Z = "-0.212" T = "1325480499647" alpha = "9.94" beta = "-0.28" gamma = "16.8" />
			<Point X = "0.278" Y = "-1.052" Z = "-0.461" T = "1325480499680" alpha = "8.26" beta = "1.82" gamma = "12.18" />
		</Stroke>
	</Gesture>
	<Gesture Name="shake">
		<Stroke>
			<Point X = "0.059" Y = "1.498" Z = "0.291" T = "1325480540363" alpha = "-10.01" beta = "-5.46" gamma = "10.15" />
			<Point X = "0.416" Y = "0.557" Z = "-0.286" T = "1325480540403" alpha = "6.65" beta = "-7.56" gamma = "31.08" />
			<Point X = "1.296" Y = "-1.976" Z = "-0.271" T = "1325480540444" alpha = "4.97" beta = "-6.37" gamma = "36.82" />
			<Point X = "0.099" Y = "-3.732" Z = "0.381" T = "1325480540480" alpha = "7.42" beta = "0.35" gamma = "14.14" />
			<Point X = "-0.863" Y = "-2.873" Z = "0.019" T = "1325480540520" alpha = "-0.84" beta = "-6.44" gamma = "-25.62" />
			<Point X = "-1.035" Y = "-0.608" Z = "-0.419" T = "1325480540560" alpha = "-21" beta = "-8.89" gamma = "-59.92" />
			<Point X = "-0.562" Y = "2.061" Z = "-0.316" T = "1325480540606" alpha = "-25.83" beta = "-8.33" gamma = "-64.89" />
			<Point X = "-0.143" Y = "4.844" Z = "0.103" T = "1325480540639" alpha = "-7.7" beta = "-6.93" gamma = "-33.11" />
			<Point X = "-0.168" Y = "4.524" Z = "0.245" T = "1325480540683" alpha = "10.36" beta = "-9.87" gamma = "24.5" />
			<Point X = "-0.267" Y = "3.028" Z = "0.278" T = "1325480540719" alpha = "14.7" beta = "-11.41" gamma = "74.27" />
			<Point X = "-0.395" Y = "0.364" Z = "-0.024" T = "1325480540759" alpha = "32.2" beta = "-8.19" gamma = "106.19" />
			<Point X = "0.287" Y = "-1.548" Z = "-0.211" T = "1325480540806" alpha = "36.89" beta = "-1.96" gamma = "117.18" />
			<Point X = "0.867" Y = "-4.696" Z = "-0.404" T = "1325480540841" alpha = "16.17" beta = "4.9" gamma = "97.09" />
			<Point X = "0.684" Y = "-6.944" Z = "0.372" T = "1325480540884" alpha = "27.3" beta = "8.26" gamma = "52.99" />
			<Point X = "0.134" Y = "-7.037" Z = "-0.824" T = "1325480540920" alpha = "8.82" beta = "2.66" gamma = "-19.6" />
			<Point X = "-0.339" Y = "-3.384" Z = "-0.857" T = "1325480540963" alpha = "-2.66" beta = "4.34" gamma = "-98.28" />
			<Point X = "-0.905" Y = "0.827" Z = "0.046" T = "1325480541003" alpha = "-35.35" beta = "20.65" gamma = "-167.51" />
			<Point X = "-1.097" Y = "7.449" Z = "1.71" T = "1325480541046" alpha = "-36.4" beta = "22.4" gamma = "-154.07" />
			<Point X = "-0.233" Y = "9.853" Z = "1.132" T = "1325480541080" alpha = "-23.87" beta = "-1.4" gamma = "-50.12" />
			<Point X = "-0.343" Y = "7.006" Z = "0.155" T = "1325480541125" alpha = "-7.21" beta = "-23.59" gamma = "60.55" />
			<Point X = "-0.387" Y = "2.283" Z = "0.082" T = "1325480541158" alpha = "19.53" beta = "-26.32" gamma = "111.58" />
			<Point X = "-0.036" Y = "-1.246" Z = "-0.196" T = "1325480541203" alpha = "26.25" beta = "-10.36" gamma = "130.55" />
			<Point X = "0.402" Y = "-4.921" Z = "-0.425" T = "1325480541247" alpha = "19.88" beta = "-1.47" gamma = "122.43" />
			<Point X = "0.775" Y = "-9.057" Z = "-0.03" T = "1325480541279" alpha = "33.74" beta = "-3.43" gamma = "80.64" />
			<Point X = "0.62" Y = "-8.921" Z = "-0.995" T = "1325480541319" alpha = "16.87" beta = "-9.38" gamma = "-10.92" />
			<Point X = "0.146" Y = "-3.836" Z = "-1.27" T = "1325480541364" alpha = "-8.68" beta = "0.91" gamma = "-108.29" />
			<Point X = "-0.517" Y = "1.29" Z = "-0.237" T = "1325480541400" alpha = "-72.1" beta = "22.89" gamma = "-172.27" />
			<Point X = "-0.919" Y = "6.587" Z = "1.566" T = "1325480541445" alpha = "-41.93" beta = "23.52" gamma = "-152.46" />
			<Point X = "-0.153" Y = "9.774" Z = "1.241" T = "1325480541484" alpha = "-31.36" beta = "1.26" gamma = "-52.85" />
			<Point X = "-0.121" Y = "5.941" Z = "0.543" T = "1325480541527" alpha = "-14.49" beta = "-19.39" gamma = "34.93" />
			<Point X = "-0.382" Y = "2.366" Z = "1.152" T = "1325480541558" alpha = "25.2" beta = "-20.93" gamma = "81.48" />
			<Point X = "-0.078" Y = "-0.475" Z = "0.319" T = "1325480541599" alpha = "37.73" beta = "-16.24" gamma = "102.27" />
			<Point X = "-0.005" Y = "-2.034" Z = "-0.061" T = "1325480541640" alpha = "26.39" beta = "-15.61" gamma = "103.95" />
			<Point X = "1.495" Y = "-5.72" Z = "-1.747" T = "1325480541684" alpha = "23.94" beta = "-21.21" gamma = "95.83" />
			<Point X = "1.215" Y = "-5.65" Z = "-1.148" T = "1325480541723" alpha = "31.92" beta = "-17.15" gamma = "66.15" />
			<Point X = "0.861" Y = "-5.18" Z = "-1.282" T = "1325480541761" alpha = "8.96" beta = "-6.72" gamma = "9.73" />
			<Point X = "0.62" Y = "-3.815" Z = "-1.506" T = "1325480541806" alpha = "-4.2" beta = "8.54" gamma = "-51.38" />
			<Point X = "-0.092" Y = "-0.891" Z = "-0.541" T = "1325480541849" alpha = "-30.17" beta = "19.95" gamma = "-98" />
			<Point X = "-0.749" Y = "2.377" Z = "0.909" T = "1325480541879" alpha = "-24.64" beta = "27.23" gamma = "-120.4" />
			<Point X = "-0.488" Y = "4.604" Z = "1.17" T = "1325480541920" alpha = "-31.43" beta = "18.48" gamma = "-101.01" />
			<Point X = "0.01" Y = "4.463" Z = "0.949" T = "1325480541961" alpha = "-41.79" beta = "6.72" gamma = "-63" />
		</Stroke>
	</Gesture>
	<Gesture Name="shake">
		<Stroke>
			<Point X = "0.095" Y = "0.006" Z = "0.031" T = "1325480551478" alpha = "-0.91" beta = "0.35" gamma = "-0.77" />
			<Point X = "-0.02" Y = "0.233" Z = "-0.019" T = "1325480551526" alpha = "1.68" beta = "0.35" gamma = "2.45" />
			<Point X = "0.072" Y = "0.098" Z = "0.117" T = "1325480551564" alpha = "0.98" beta = "-0.49" gamma = "2.52" />
			<Point X = "-0.011" Y = "0.13" Z = "0.049" T = "1325480551599" alpha = "-1.75" beta = "-0.28" gamma = "4.69" />
			<Point X = "-0.015" Y = "-0.462" Z = "0.011" T = "1325480551648" alpha = "-0.28" beta = "-1.47" gamma = "2.17" />
			<Point X = "0.053" Y = "-0.071" Z = "0.024" T = "1325480551676" alpha = "1.89" beta = "-1.12" gamma = "0.84" />
			<Point X = "0.123" Y = "-0.626" Z = "-0.36" T = "1325480551720" alpha = "-2.38" beta = "2.66" gamma = "-4.62" />
			<Point X = "0.305" Y = "-1.412" Z = "-0.554" T = "1325480551767" alpha = "7.7" beta = "7.42" gamma = "-14.98" />
			<Point X = "-0.527" Y = "-0.31" Z = "0.361" T = "1325480551798" alpha = "11.9" beta = "17.29" gamma = "-39.13" />
			<Point X = "-0.851" Y = "2.861" Z = "1.946" T = "1325480551848" alpha = "-3.29" beta = "11.69" gamma = "-51.59" />
			<Point X = "-0.633" Y = "5.704" Z = "1.854" T = "1325480551879" alpha = "15.19" beta = "-18.83" gamma = "5.53" />
			<Point X = "-0.336" Y = "4.423" Z = "-0.582" T = "1325480551921" alpha = "57.68" beta = "-44.52" gamma = "98.7" />
			<Point X = "0.015" Y = "0.721" Z = "-1.084" T = "1325480551961" alpha = "49.91" beta = "-39.69" gamma = "142.66" />
			<Point X = "0.207" Y = "-3.591" Z = "-1.491" T = "1325480552000" alpha = "36.75" beta = "-17.64" gamma = "145.53" />
			<Point X = "1.077" Y = "-7.685" Z = "-1.243" T = "1325480552041" alpha = "27.44" beta = "-17.64" gamma = "111.86" />
			<Point X = "-0.046" Y = "-10.654" Z = "-1.53" T = "1325480552086" alpha = "1.33" beta = "5.95" gamma = "27.37" />
			<Point X = "-0.753" Y = "-5.238" Z = "-0.397" T = "1325480552119" alpha = "-9.73" beta = "20.79" gamma = "-104.65" />
			<Point X = "-1.255" Y = "0.208" Z = "0.111" T = "1325480552154" alpha = "-71.26" beta = "40.39" gamma = "-193.9" />
			<Point X = "-1.86" Y = "5.471" Z = "2.147" T = "1325480552196" alpha = "-53.13" beta = "47.53" gamma = "-194.32" />
			<Point X = "-0.772" Y = "12.409" Z = "3.542" T = "1325480552233" alpha = "-23.03" beta = "5.53" gamma = "-100.59" />
			<Point X = "-0.271" Y = "10.245" Z = "0.967" T = "1325480552272" alpha = "-8.89" beta = "-31.29" gamma = "22.68" />
			<Point X = "-0.152" Y = "4.496" Z = "0.293" T = "1325480552315" alpha = "38.71" beta = "-40.6" gamma = "112.07" />
			<Point X = "-0.192" Y = "0.074" Z = "-0.25" T = "1325480552356" alpha = "61.11" beta = "-23.8" gamma = "148.82" />
			<Point X = "0.038" Y = "-4.02" Z = "-1.203" T = "1325480552396" alpha = "53.27" beta = "-9.1" gamma = "157.43" />
			<Point X = "1.173" Y = "-8.187" Z = "-0.671" T = "1325480552439" alpha = "41.3" beta = "-5.53" gamma = "138.6" />
			<Point X = "0.238" Y = "-9.065" Z = "-0.97" T = "1325480552476" alpha = "11.06" beta = "-15.61" gamma = "77.49" />
			<Point X = "1.205" Y = "-8.311" Z = "-2.42" T = "1325480552521" alpha = "2.52" beta = "-6.72" gamma = "-41.79" />
			<Point X = "0.334" Y = "-3.107" Z = "-1.31" T = "1325480552570" alpha = "-38.57" beta = "20.23" gamma = "-141.89" />
			<Point X = "-0.544" Y = "2.43" Z = "0.257" T = "1325480552651" alpha = "-69.16" beta = "46.2" gamma = "-201.39" />
			<Point X = "-0.813" Y = "8.276" Z = "2.44" T = "1325480552671" alpha = "-35.91" beta = "44.17" gamma = "-169.33" />
			<Point X = "-0.217" Y = "9.316" Z = "2.007" T = "1325480552688" alpha = "-31.57" beta = "12.32" gamma = "-70.7" />
			<Point X = "0.148" Y = "6.073" Z = "0.98" T = "1325480552712" alpha = "-2.8" beta = "-24.15" gamma = "37.73" />
			<Point X = "0.114" Y = "1.076" Z = "0.277" T = "1325480552754" alpha = "18.13" beta = "-25.69" gamma = "81.48" />
			<Point X = "0.128" Y = "-2.137" Z = "-0.261" T = "1325480552795" alpha = "9.31" beta = "-13.23" gamma = "85.33" />
			<Point X = "0.25" Y = "-4.786" Z = "-1.195" T = "1325480552839" alpha = "6.44" beta = "-5.18" gamma = "59.15" />
			<Point X = "0.395" Y = "-3.955" Z = "-1.051" T = "1325480552883" alpha = "16.66" beta = "-2.94" gamma = "25.83" />
			<Point X = "1.026" Y = "-1.893" Z = "-0.793" T = "1325480552920" alpha = "6.3" beta = "0.98" gamma = "-9.24" />
			<Point X = "1.144" Y = "-0.655" Z = "-0.403" T = "1325480552989" alpha = "-6.16" beta = "6.72" gamma = "-24.22" />
			<Point X = "0.931" Y = "0.496" Z = "0.118" T = "1325480553005" alpha = "-8.19" beta = "7.21" gamma = "-26.18" />
			<Point X = "0.613" Y = "0.679" Z = "0.136" T = "1325480553045" alpha = "-13.51" beta = "3.85" gamma = "-20.09" />
		</Stroke>
	</Gesture>
	<Gesture Name="shake">
		<Stroke>
			<Point X = "-0.038" Y = "0.084" Z = "-0.114" T = "1325480587528" alpha = "1.89" beta = "-0.77" gamma = "2.38" />
			<Point X = "-0.065" Y = "-0.176" Z = "-0.076" T = "1325480587561" alpha = "-3.5" beta = "1.54" gamma = "0.84" />
			<Point X = "0.007" Y = "-0.068" Z = "-0.055" T = "1325480587604" alpha = "1.05" beta = "1.68" gamma = "0.77" />
			<Point X = "0.084" Y = "-0.102" Z = "-0.034" T = "1325480587648" alpha = "-0.14" beta = "1.68" gamma = "1.47" />
			<Point X = "0.039" Y = "-0.16" Z = "0.011" T = "1325480587681" alpha = "-1.68" beta = "2.87" gamma = "0.91" />
			<Point X = "0.037" Y = "-0.31" Z = "0.131" T = "1325480587722" alpha = "-3.01" beta = "2.66" gamma = "-0.49" />
			<Point X = "0.514" Y = "-1.058" Z = "0.078" T = "1325480587774" alpha = "-5.74" beta = "0.56" gamma = "-2.45" />
			<Point X = "0.195" Y = "-1.861" Z = "-0.288" T = "1325480587796" alpha = "7.56" beta = "3.22" gamma = "-20.93" />
			<Point X = "-1.02" Y = "0.521" Z = "0.677" T = "1325480587849" alpha = "11.83" beta = "7.84" gamma = "-52.92" />
			<Point X = "-1.177" Y = "4.014" Z = "1.355" T = "1325480587883" alpha = "-3.85" beta = "6.72" gamma = "-60.13" />
			<Point X = "-0.58" Y = "5.581" Z = "0.353" T = "1325480587924" alpha = "30.66" beta = "-14.77" gamma = "-1.05" />
			<Point X = "-0.215" Y = "5.185" Z = "-0.028" T = "1325480587961" alpha = "38.29" beta = "-29.05" gamma = "84.14" />
			<Point X = "0.048" Y = "1.071" Z = "-0.796" T = "1325480588005" alpha = "27.3" beta = "-24.22" gamma = "134.05" />
			<Point X = "-0.314" Y = "-4.564" Z = "-0.629" T = "1325480588056" alpha = "28.7" beta = "-7.49" gamma = "148.89" />
			<Point X = "0.214" Y = "-7.304" Z = "-0.379" T = "1325480588081" alpha = "20.02" beta = "-3.71" gamma = "113.89" />
			<Point X = "-0.007" Y = "-8.954" Z = "-1.226" T = "1325480588121" alpha = "-33.81" beta = "-10.5" gamma = "37.24" />
			<Point X = "0.575" Y = "-6.397" Z = "-1.597" T = "1325480588169" alpha = "-44.59" beta = "2.38" gamma = "-77.14" />
			<Point X = "0.31" Y = "-2.7" Z = "-1.829" T = "1325480588234" alpha = "-64.47" beta = "32.69" gamma = "-154.07" />
			<Point X = "-0.81" Y = "2.991" Z = "1.554" T = "1325480588240" alpha = "-67.13" beta = "58.52" gamma = "-194.6" />
			<Point X = "-0.767" Y = "7.784" Z = "3.586" T = "1325480588274" alpha = "-16.03" beta = "42" gamma = "-155.61" />
			<Point X = "-0.954" Y = "9.768" Z = "2.921" T = "1325480588313" alpha = "-2.59" beta = "0.56" gamma = "-53.55" />
			<Point X = "-0.928" Y = "6.819" Z = "1.906" T = "1325480588366" alpha = "7.63" beta = "-41.72" gamma = "42.42" />
			<Point X = "-0.857" Y = "3.687" Z = "0.139" T = "1325480588408" alpha = "47.11" beta = "-52.29" gamma = "107.52" />
			<Point X = "-0.753" Y = "0.281" Z = "-0.986" T = "1325480588442" alpha = "51.8" beta = "-43.05" gamma = "140.21" />
			<Point X = "0.322" Y = "-2.796" Z = "-2.148" T = "1325480588484" alpha = "48.51" beta = "-24.36" gamma = "150.85" />
			<Point X = "1.772" Y = "-6.921" Z = "-2.499" T = "1325480588527" alpha = "20.09" beta = "-4.55" gamma = "135.59" />
			<Point X = "1.374" Y = "-9.164" Z = "-0.725" T = "1325480588558" alpha = "48.02" beta = "4.76" gamma = "91.91" />
			<Point X = "1.288" Y = "-8.377" Z = "-1.497" T = "1325480588605" alpha = "28.07" beta = "5.32" gamma = "7.98" />
			<Point X = "0.715" Y = "-3.658" Z = "-0.793" T = "1325480588695" alpha = "-30.38" beta = "9.17" gamma = "-86.94" />
			<Point X = "0.078" Y = "-1.272" Z = "-0.753" T = "1325480588726" alpha = "-75.88" beta = "30.59" gamma = "-159.95" />
			<Point X = "-1.377" Y = "2.815" Z = "0.804" T = "1325480588730" alpha = "-37.73" beta = "49.21" gamma = "-185.01" />
			<Point X = "-1.749" Y = "6.532" Z = "2.542" T = "1325480588755" alpha = "-12.53" beta = "36.05" gamma = "-168.7" />
			<Point X = "-1.43" Y = "9.221" Z = "2.627" T = "1325480588796" alpha = "-22.96" beta = "5.18" gamma = "-93.24" />
			<Point X = "-0.646" Y = "7.367" Z = "1.244" T = "1325480588846" alpha = "-4.76" beta = "-22.33" gamma = "-9.31" />
			<Point X = "-0.157" Y = "3.721" Z = "0.235" T = "1325480588888" alpha = "20.23" beta = "-27.79" gamma = "57.89" />
			<Point X = "-0.334" Y = "1.495" Z = "0.173" T = "1325480588921" alpha = "36.19" beta = "-16.87" gamma = "92.33" />
			<Point X = "-0.181" Y = "-0.291" Z = "0.054" T = "1325480588971" alpha = "29.82" beta = "-14.42" gamma = "110.39" />
			<Point X = "1.383" Y = "-2.708" Z = "-0.962" T = "1325480589005" alpha = "39.97" beta = "-18.76" gamma = "127.4" />
			<Point X = "3.388" Y = "-6.573" Z = "-2.274" T = "1325480589056" alpha = "22.54" beta = "-19.67" gamma = "129.01" />
			<Point X = "1.175" Y = "-7.984" Z = "-0.55" T = "1325480589083" alpha = "26.39" beta = "-11.69" gamma = "86.52" />
			<Point X = "1.001" Y = "-5.951" Z = "-1.263" T = "1325480589123" alpha = "-1.12" beta = "-12.88" gamma = "0.28" />
			<Point X = "0.78" Y = "-3.157" Z = "-2.035" T = "1325480589174" alpha = "-23.73" beta = "0.56" gamma = "-65.8" />
		</Stroke>
	</Gesture>
	<Gesture Name="shake">
		<Stroke>
			<Point X = "-0.091" Y = "-0.165" Z = "0.108" T = "1325480592083" alpha = "4.34" beta = "1.54" gamma = "-9.24" />
			<Point X = "-0.042" Y = "0.214" Z = "-0.023" T = "1325480592123" alpha = "1.68" beta = "3.36" gamma = "-10.36" />
			<Point X = "-0.041" Y = "-0.089" Z = "-0.25" T = "1325480592164" alpha = "-3.71" beta = "3.99" gamma = "-10.36" />
			<Point X = "-0.094" Y = "0.114" Z = "-0.162" T = "1325480592205" alpha = "9.45" beta = "5.46" gamma = "-6.65" />
			<Point X = "-0.112" Y = "0.342" Z = "0.116" T = "1325480592242" alpha = "0.77" beta = "6.65" gamma = "-3.78" />
			<Point X = "-0.028" Y = "-0.191" Z = "0.048" T = "1325480592280" alpha = "14.7" beta = "5.04" gamma = "2.73" />
			<Point X = "-0.08" Y = "0.396" Z = "0.36" T = "1325480592322" alpha = "21.21" beta = "4.27" gamma = "4.97" />
			<Point X = "-0.077" Y = "0.514" Z = "0.103" T = "1325480592364" alpha = "3.78" beta = "5.39" gamma = "2.73" />
			<Point X = "-0.137" Y = "0.291" Z = "0.006" T = "1325480592405" alpha = "-20.09" beta = "7.84" gamma = "-1.33" />
			<Point X = "-0.314" Y = "-0.16" Z = "-0.315" T = "1325480592445" alpha = "-14.84" beta = "10.36" gamma = "-3.15" />
			<Point X = "-0.374" Y = "0.169" Z = "0.067" T = "1325480592484" alpha = "23.66" beta = "8.12" gamma = "-1.89" />
			<Point X = "-0.408" Y = "0.616" Z = "0.222" T = "1325480592521" alpha = "18.27" beta = "5.04" gamma = "0.98" />
			<Point X = "-0.367" Y = "0.215" Z = "0.063" T = "1325480592569" alpha = "1.47" beta = "3.22" gamma = "4.9" />
			<Point X = "-0.345" Y = "-0.02" Z = "-0.143" T = "1325480592603" alpha = "10.71" beta = "1.68" gamma = "5.74" />
			<Point X = "-0.316" Y = "0.317" Z = "0.092" T = "1325480592641" alpha = "15.54" beta = "-1.4" gamma = "4.76" />
			<Point X = "-0.33" Y = "0.131" Z = "0.011" T = "1325480592691" alpha = "1.54" beta = "-4.83" gamma = "1.82" />
			<Point X = "-0.352" Y = "-0.19" Z = "-0.166" T = "1325480592722" alpha = "-8.75" beta = "-4.55" gamma = "-3.29" />
			<Point X = "-0.39" Y = "-0.142" Z = "-0.033" T = "1325480592763" alpha = "-11.76" beta = "-1.4" gamma = "-10.15" />
			<Point X = "-0.527" Y = "0.273" Z = "0.138" T = "1325480592801" alpha = "-14.21" beta = "0.98" gamma = "-9.1" />
			<Point X = "-0.132" Y = "0.389" Z = "0.181" T = "1325480592850" alpha = "-14.98" beta = "-5.6" gamma = "-5.46" />
			<Point X = "-0.301" Y = "-0.885" Z = "-0.316" T = "1325480592883" alpha = "-17.5" beta = "-5.04" gamma = "-1.89" />
			<Point X = "0.781" Y = "-2.462" Z = "-1.869" T = "1325480592925" alpha = "-27.86" beta = "6.86" gamma = "-17.5" />
			<Point X = "0.535" Y = "-1.432" Z = "-0.448" T = "1325480592971" alpha = "-60.34" beta = "42.84" gamma = "-53.2" />
			<Point X = "-0.211" Y = "-0.661" Z = "1.631" T = "1325480593003" alpha = "-26.32" beta = "48.86" gamma = "-67.76" />
			<Point X = "-2.43" Y = "4.651" Z = "5.478" T = "1325480593048" alpha = "30.38" beta = "24.92" gamma = "-37.59" />
			<Point X = "-2.156" Y = "6.219" Z = "2.973" T = "1325480593083" alpha = "43.89" beta = "-55.3" gamma = "61.18" />
			<Point X = "-0.709" Y = "2.542" Z = "-1.09" T = "1325480593124" alpha = "47.25" beta = "-88.48" gamma = "139.65" />
			<Point X = "1.68" Y = "-3.606" Z = "-4.188" T = "1325480593165" alpha = "34.93" beta = "-65.24" gamma = "145.25" />
			<Point X = "4.03" Y = "-9.157" Z = "-3.664" T = "1325480593203" alpha = "47.18" beta = "-23.17" gamma = "89.04" />
			<Point X = "1.706" Y = "-10.877" Z = "-1.936" T = "1325480593241" alpha = "8.12" beta = "-14.49" gamma = "22.33" />
			<Point X = "-0.142" Y = "-2.476" Z = "0.144" T = "1325480593282" alpha = "-44.66" beta = "8.54" gamma = "-118.16" />
			<Point X = "-0.785" Y = "2.043" Z = "1.771" T = "1325480593320" alpha = "-175.42" beta = "38.22" gamma = "-191.17" />
			<Point X = "-2.833" Y = "9.915" Z = "4.755" T = "1325480593360" alpha = "-33.46" beta = "18.62" gamma = "-103.74" />
			<Point X = "-1.47" Y = "10.314" Z = "1.712" T = "1325480593403" alpha = "-2.66" beta = "-46.62" gamma = "14.21" />
			<Point X = "1.197" Y = "3.856" Z = "-1.263" T = "1325480593448" alpha = "42.84" beta = "-75.6" gamma = "104.37" />
			<Point X = "2.956" Y = "-2.563" Z = "-3.192" T = "1325480593486" alpha = "48.79" beta = "-42.21" gamma = "120.96" />
			<Point X = "3.523" Y = "-6.344" Z = "-1.493" T = "1325480593523" alpha = "56" beta = "-7.63" gamma = "107.52" />
			<Point X = "0.707" Y = "-9.928" Z = "-1.501" T = "1325480593563" alpha = "13.37" beta = "-4.48" gamma = "37.52" />
			<Point X = "0.099" Y = "-6.531" Z = "-1.12" T = "1325480593607" alpha = "-17.01" beta = "8.96" gamma = "-75.6" />
			<Point X = "-1.405" Y = "0.504" Z = "0.032" T = "1325480593644" alpha = "-103.6" beta = "49.07" gamma = "-174.44" />
			<Point X = "-2.594" Y = "4.284" Z = "2.887" T = "1325480593683" alpha = "-48.09" beta = "73.15" gamma = "-178.15" />
			<Point X = "-2.213" Y = "11.551" Z = "3.409" T = "1325480593722" alpha = "21.98" beta = "18.27" gamma = "-73.57" />
			<Point X = "-0.495" Y = "7.845" Z = "0.388" T = "1325480593765" alpha = "14.63" beta = "-44.94" gamma = "64.54" />
			<Point X = "1.11" Y = "1.259" Z = "-0.712" T = "1325480593806" alpha = "45.78" beta = "-50.96" gamma = "122.92" />
			<Point X = "1.413" Y = "-3.225" Z = "-1.13" T = "1325480593844" alpha = "56.49" beta = "-20.44" gamma = "123.76" />
			<Point X = "0.732" Y = "-6.068" Z = "-1.09" T = "1325480593883" alpha = "19.32" beta = "-3.36" gamma = "93.8" />
			<Point X = "0.821" Y = "-5.865" Z = "-1.822" T = "1325480593925" alpha = "7.42" beta = "-5.32" gamma = "56.42" />
			<Point X = "0.634" Y = "-6.07" Z = "-1.633" T = "1325480593964" alpha = "-20.23" beta = "3.78" gamma = "-19.04" />
			<Point X = "0.392" Y = "-2.477" Z = "-0.886" T = "1325480594006" alpha = "-33.46" beta = "17.15" gamma = "-81.9" />
			<Point X = "-0.14" Y = "1.301" Z = "0.463" T = "1325480594044" alpha = "-54.46" beta = "39.41" gamma = "-125.02" />
			<Point X = "-0.125" Y = "4.181" Z = "0.929" T = "1325480594084" alpha = "-26.32" beta = "32.9" gamma = "-103.25" />
			<Point X = "-0.098" Y = "4.761" Z = "0.939" T = "1325480594131" alpha = "-32.55" beta = "18.9" gamma = "-55.02" />
			<Point X = "0.12" Y = "2.588" Z = "0.939" T = "1325480594164" alpha = "-14.14" beta = "7.14" gamma = "-22.47" />
			<Point X = "-0.015" Y = "1.387" Z = "0.919" T = "1325480594204" alpha = "3.36" beta = "4.97" gamma = "4.55" />
			<Point X = "-0.322" Y = "-0.058" Z = "0.441" T = "1325480594248" alpha = "0.35" beta = "4.76" gamma = "11.55" />
			<Point X = "-0.332" Y = "-1.036" Z = "0.06" T = "1325480594284" alpha = "5.04" beta = "2.03" gamma = "8.54" />
			<Point X = "-0.093" Y = "-0.599" Z = "-0.109" T = "1325480594332" alpha = "13.65" beta = "0.07" gamma = "3.57" />
			<Point X = "0.157" Y = "-0.39" Z = "-0.275" T = "1325480594362" alpha = "3.22" beta = "0.42" gamma = "2.8" />
			<Point X = "0.202" Y = "-0.522" Z = "-0.683" T = "1325480594399" alpha = "-0.56" beta = "-0.14" gamma = "6.86" />
		</Stroke>
	</Gesture>
	<Gesture Name="shake">
		<Stroke>
			<Point X = "0.122" Y = "-0.128" Z = "0.122" T = "1325480595841" alpha = "-0.42" beta = "2.52" gamma = "-0.42" />
			<Point X = "-0.015" Y = "0.026" Z = "0.099" T = "1325480595877" alpha = "2.38" beta = "3.08" gamma = "-1.33" />
			<Point X = "-0.043" Y = "-0.22" Z = "-0.026" T = "1325480595924" alpha = "-3.99" beta = "1.61" gamma = "-2.66" />
			<Point X = "-0.017" Y = "-0.063" Z = "-0.013" T = "1325480595964" alpha = "2.17" beta = "0.56" gamma = "-1.82" />
			<Point X = "-0.027" Y = "0.145" Z = "0.068" T = "1325480596007" alpha = "-0.49" beta = "0.35" gamma = "-1.82" />
			<Point X = "0.034" Y = "-0.193" Z = "-0.146" T = "1325480596039" alpha = "-6.93" beta = "2.31" gamma = "-2.1" />
			<Point X = "-0.07" Y = "-0.102" Z = "-0.094" T = "1325480596084" alpha = "-0.28" beta = "3.78" gamma = "-3.43" />
			<Point X = "0.013" Y = "0.228" Z = "0.33" T = "1325480596127" alpha = "0.56" beta = "1.54" gamma = "-4.34" />
			<Point X = "0.102" Y = "0.117" Z = "0.042" T = "1325480596163" alpha = "-6.79" beta = "1.05" gamma = "-3.36" />
			<Point X = "0.06" Y = "-0.017" Z = "-0.05" T = "1325480596205" alpha = "-5.18" beta = "2.03" gamma = "-2.8" />
			<Point X = "-0.304" Y = "-0.084" Z = "0.069" T = "1325480596244" alpha = "-0.7" beta = "6.3" gamma = "-4.62" />
			<Point X = "-0.446" Y = "1.012" Z = "1.031" T = "1325480596280" alpha = "4.06" beta = "9.03" gamma = "-11.13" />
			<Point X = "-0.412" Y = "3.323" Z = "1.914" T = "1325480596326" alpha = "17.71" beta = "-4.76" gamma = "5.46" />
			<Point X = "0.135" Y = "3.665" Z = "0.636" T = "1325480596361" alpha = "48.72" beta = "-34.65" gamma = "74.97" />
			<Point X = "0.21" Y = "1.772" Z = "-0.797" T = "1325480596403" alpha = "73.78" beta = "-51.94" gamma = "136.22" />
			<Point X = "1.2" Y = "-3.653" Z = "-2.075" T = "1325480596445" alpha = "70.21" beta = "-42.84" gamma = "156.03" />
			<Point X = "0.674" Y = "-8.376" Z = "-1.314" T = "1325480596488" alpha = "44.17" beta = "-18.06" gamma = "111.79" />
			<Point X = "-1.114" Y = "-10.082" Z = "-0.174" T = "1325480596522" alpha = "-16.59" beta = "-4.62" gamma = "-0.77" />
			<Point X = "-1.854" Y = "-4.539" Z = "-1.139" T = "1325480596572" alpha = "-16.03" beta = "16.45" gamma = "-153.23" />
			<Point X = "-1.88" Y = "2.289" Z = "0.236" T = "1325480596630" alpha = "-16.03" beta = "16.45" gamma = "-153.23" />
			<Point X = "-1.347" Y = "10.25" Z = "2.983" T = "1325480596659" alpha = "-99.61" beta = "42.49" gamma = "-222.81" />
			<Point X = "-0.111" Y = "12.385" Z = "1.332" T = "1325480596674" alpha = "-1.96" beta = "-14.77" gamma = "-37.8" />
			<Point X = "1.077" Y = "6.868" Z = "-0.941" T = "1325480596718" alpha = "6.72" beta = "-53.41" gamma = "81.62" />
			<Point X = "1.126" Y = "0.908" Z = "-1.409" T = "1325480596758" alpha = "35.91" beta = "-35.21" gamma = "145.32" />
			<Point X = "0.189" Y = "-4.285" Z = "0.251" T = "1325480596801" alpha = "52.43" beta = "-3.71" gamma = "139.37" />
			<Point X = "0.61" Y = "-7.737" Z = "-0.054" T = "1325480596843" alpha = "53.2" beta = "1.75" gamma = "108.15" />
			<Point X = "0.653" Y = "-9.373" Z = "-1.354" T = "1325480596881" alpha = "2.52" beta = "-7.98" gamma = "7.14" />
			<Point X = "0.034" Y = "-4.405" Z = "-0.902" T = "1325480596921" alpha = "-30.45" beta = "8.54" gamma = "-98.91" />
			<Point X = "-0.507" Y = "2.083" Z = "0.887" T = "1325480596968" alpha = "-81.76" beta = "39.27" gamma = "-174.37" />
			<Point X = "-0.922" Y = "7.086" Z = "2.335" T = "1325480597000" alpha = "-18.69" beta = "37.31" gamma = "-137.48" />
			<Point X = "-0.045" Y = "11.059" Z = "0.916" T = "1325480597056" alpha = "12.18" beta = "-9.1" gamma = "-6.09" />
			<Point X = "0.837" Y = "4.119" Z = "-0.747" T = "1325480597087" alpha = "27.51" beta = "-41.79" gamma = "98.63" />
			<Point X = "0.576" Y = "-1.401" Z = "-1.162" T = "1325480597124" alpha = "51.94" beta = "-22.89" gamma = "133.14" />
			<Point X = "0.531" Y = "-5.481" Z = "0.041" T = "1325480597166" alpha = "41.86" beta = "0.91" gamma = "116.34" />
			<Point X = "0.215" Y = "-6.772" Z = "-0.105" T = "1325480597209" alpha = "13.58" beta = "-1.96" gamma = "65.1" />
			<Point X = "0.972" Y = "-7.485" Z = "-2.169" T = "1325480597243" alpha = "-16.94" beta = "-7.56" gamma = "-9.03" />
			<Point X = "0.561" Y = "-3.448" Z = "-1.209" T = "1325480597283" alpha = "-20.09" beta = "7.98" gamma = "-90.44" />
			<Point X = "-0.326" Y = "0.326" Z = "0.063" T = "1325480597329" alpha = "-62.86" beta = "37.03" gamma = "-158.97" />
			<Point X = "-1.511" Y = "4.332" Z = "1.97" T = "1325480597361" alpha = "-54.04" beta = "53.55" gamma = "-172.41" />
			<Point X = "-1.159" Y = "7.861" Z = "2.296" T = "1325480597410" alpha = "-51.17" beta = "28.49" gamma = "-107.94" />
			<Point X = "-0.992" Y = "6.656" Z = "0.951" T = "1325480597442" alpha = "-8.4" beta = "-13.93" gamma = "-7.56" />
			<Point X = "0.355" Y = "3.108" Z = "0.28" T = "1325480597481" alpha = "21.14" beta = "-29.12" gamma = "62.51" />
			<Point X = "0.391" Y = "0.337" Z = "-0.383" T = "1325480597535" alpha = "33.81" beta = "-15.75" gamma = "87.99" />
			<Point X = "-0.164" Y = "-2.137" Z = "0.01" T = "1325480597563" alpha = "25.41" beta = "0.42" gamma = "86.94" />
			<Point X = "0.051" Y = "-3.886" Z = "-0.415" T = "1325480597601" alpha = "17.08" beta = "-0.35" gamma = "71.05" />
			<Point X = "0.462" Y = "-4.175" Z = "-0.69" T = "1325480597649" alpha = "16.45" beta = "-7.21" gamma = "45.29" />
			<Point X = "0.676" Y = "-2.609" Z = "-0.864" T = "1325480597684" alpha = "2.8" beta = "-8.26" gamma = "12.74" />
			<Point X = "0.776" Y = "-1.7" Z = "-1.495" T = "1325480597724" alpha = "-3.5" beta = "0.21" gamma = "-13.72" />
			<Point X = "0.747" Y = "-0.503" Z = "-0.574" T = "1325480597767" alpha = "-7.84" beta = "11.34" gamma = "-30.45" />
			<Point X = "0.469" Y = "0.23" Z = "-0.088" T = "1325480597810" alpha = "-25.06" beta = "17.64" gamma = "-36.96" />
		</Stroke>
	</Gesture>
	<Gesture Name="shake">
		<Stroke>
			<Point X = "0.04" Y = "0.083" Z = "-0.155" T = "1325480653289" alpha = "-0.49" beta = "0.56" gamma = "-1.54" />
			<Point X = "0.034" Y = "-0.01" Z = "0.067" T = "1325480653333" alpha = "2.66" beta = "0.84" gamma = "-0.84" />
			<Point X = "-0.049" Y = "0.036" Z = "0.027" T = "1325480653362" alpha = "1.26" beta = "0.49" gamma = "0.56" />
			<Point X = "-0.022" Y = "-0.14" Z = "0.037" T = "1325480653409" alpha = "-3.15" beta = "0.28" gamma = "-0.35" />
			<Point X = "-0.037" Y = "-0.077" Z = "0.081" T = "1325480653459" alpha = "0.77" beta = "0.28" gamma = "-1.47" />
			<Point X = "-0.072" Y = "0.235" Z = "0.046" T = "1325480653490" alpha = "0.7" beta = "0.28" gamma = "-1.26" />
			<Point X = "-0.065" Y = "1.237" Z = "0.643" T = "1325480653531" alpha = "3.92" beta = "-3.43" gamma = "3.29" />
			<Point X = "0.09" Y = "1.935" Z = "0.39" T = "1325480653574" alpha = "13.58" beta = "-14.98" gamma = "28.49" />
			<Point X = "0.231" Y = "1.232" Z = "-0.442" T = "1325480653609" alpha = "51.8" beta = "-25.69" gamma = "65.03" />
			<Point X = "1.425" Y = "-0.572" Z = "-0.723" T = "1325480653649" alpha = "45.43" beta = "-25.62" gamma = "86.87" />
			<Point X = "1.967" Y = "-7.414" Z = "-1.652" T = "1325480653694" alpha = "30.31" beta = "-3.01" gamma = "61.6" />
			<Point X = "-1.371" Y = "-5.378" Z = "0.233" T = "1325480653736" alpha = "43.05" beta = "6.3" gamma = "-14.28" />
			<Point X = "-2.565" Y = "-0.208" Z = "0.427" T = "1325480653770" alpha = "-51.03" beta = "18.41" gamma = "-139.65" />
			<Point X = "-1.801" Y = "4.359" Z = "1.418" T = "1325480653815" alpha = "-58.24" beta = "23.31" gamma = "-160.65" />
			<Point X = "-0.995" Y = "9.023" Z = "1.172" T = "1325480653849" alpha = "-4.97" beta = "1.47" gamma = "-86.87" />
			<Point X = "-0.493" Y = "9.311" Z = "-0.237" T = "1325480653895" alpha = "5.46" beta = "-26.46" gamma = "44.59" />
			<Point X = "0.036" Y = "3.134" Z = "-0.827" T = "1325480653930" alpha = "18.62" beta = "-22.19" gamma = "111.72" />
			<Point X = "0.502" Y = "-2.196" Z = "0.376" T = "1325480653971" alpha = "34.93" beta = "1.26" gamma = "135.38" />
			<Point X = "0.939" Y = "-6.881" Z = "0.067" T = "1325480654008" alpha = "-2.38" beta = "7.98" gamma = "131.88" />
			<Point X = "0.198" Y = "-10.855" Z = "-0.44" T = "1325480654048" alpha = "28.7" beta = "-6.09" gamma = "85.75" />
			<Point X = "0.044" Y = "-7.436" Z = "-1.034" T = "1325480654094" alpha = "6.02" beta = "-10.01" gamma = "-35.28" />
			<Point X = "0.066" Y = "-0.953" Z = "-1.061" T = "1325480654128" alpha = "-56.28" beta = "7.7" gamma = "-141.89" />
			<Point X = "-0.524" Y = "5.578" Z = "1.732" T = "1325480654172" alpha = "-19.46" beta = "29.19" gamma = "-151.55" />
			<Point X = "0.15" Y = "10.299" Z = "1.439" T = "1325480654208" alpha = "8.26" beta = "1.47" gamma = "-68.95" />
			<Point X = "0.525" Y = "9.585" Z = "-0.642" T = "1325480654247" alpha = "13.58" beta = "-26.6" gamma = "62.58" />
			<Point X = "0.593" Y = "2.009" Z = "-0.885" T = "1325480654295" alpha = "28.7" beta = "-23.17" gamma = "137.2" />
			<Point X = "0.131" Y = "-4.141" Z = "0.997" T = "1325480654329" alpha = "45.22" beta = "-3.85" gamma = "140.21" />
			<Point X = "0.098" Y = "-8.654" Z = "0.815" T = "1325480654370" alpha = "44.94" beta = "-3.64" gamma = "99.26" />
			<Point X = "-0.27" Y = "-10.026" Z = "-1.672" T = "1325480654406" alpha = "-11.41" beta = "-21.42" gamma = "17.78" />
			<Point X = "-0.352" Y = "-5.394" Z = "-2.268" T = "1325480654452" alpha = "-16.45" beta = "-9.45" gamma = "-75.53" />
			<Point X = "-0.835" Y = "-0.041" Z = "-1.768" T = "1325480654573" alpha = "-55.93" beta = "28.42" gamma = "-163.24" />
			<Point X = "-0.898" Y = "5.386" Z = "1.451" T = "1325480654579" alpha = "-34.16" beta = "52.99" gamma = "-171.99" />
			<Point X = "0.208" Y = "10.71" Z = "2.815" T = "1325480654583" alpha = "-21" beta = "27.3" gamma = "-101.5" />
			<Point X = "0.973" Y = "9.625" Z = "1.203" T = "1325480654600" alpha = "-4.83" beta = "-20.09" gamma = "57.33" />
			<Point X = "0.916" Y = "1.425" Z = "0.187" T = "1325480654646" alpha = "25.06" beta = "-32.2" gamma = "127.75" />
			<Point X = "0.015" Y = "-3.127" Z = "0.749" T = "1325480654688" alpha = "41.79" beta = "-22.96" gamma = "135.45" />
			<Point X = "-0.476" Y = "-6.121" Z = "0.065" T = "1325480654729" alpha = "19.25" beta = "-20.93" gamma = "99.54" />
		</Stroke>
	</Gesture>
	<Gesture Name="shake">
		<Stroke>
			<Point X = "-0.013" Y = "0.414" Z = "0.038" T = "1325480660093" alpha = "-1.96" beta = "-1.96" gamma = "-8.05" />
			<Point X = "-0.152" Y = "0.351" Z = "-0.173" T = "1325480660130" alpha = "-1.26" beta = "-1.68" gamma = "-4.06" />
			<Point X = "-0.034" Y = "0.43" Z = "-0.106" T = "1325480660171" alpha = "-0.35" beta = "0.21" gamma = "-0.84" />
			<Point X = "0.063" Y = "-0.169" Z = "0.032" T = "1325480660217" alpha = "-2.8" beta = "2.24" gamma = "0.42" />
			<Point X = "-0.088" Y = "-0.114" Z = "0.164" T = "1325480660250" alpha = "1.75" beta = "2.66" gamma = "0.7" />
			<Point X = "-0.147" Y = "0.781" Z = "0.768" T = "1325480660291" alpha = "1.12" beta = "-2.87" gamma = "1.82" />
			<Point X = "0.128" Y = "2.488" Z = "1.145" T = "1325480660330" alpha = "1.19" beta = "-16.31" gamma = "24.01" />
			<Point X = "0.204" Y = "1.722" Z = "-0.334" T = "1325480660370" alpha = "22.68" beta = "-30.1" gamma = "67.48" />
			<Point X = "1.629" Y = "-2.003" Z = "-1.108" T = "1325480660413" alpha = "32.9" beta = "-33.18" gamma = "91" />
			<Point X = "1.531" Y = "-6.495" Z = "-1.989" T = "1325480660451" alpha = "35.14" beta = "-12.67" gamma = "71.26" />
			<Point X = "-1.229" Y = "-6.743" Z = "-0.756" T = "1325480660489" alpha = "15.12" beta = "3.99" gamma = "-25.69" />
			<Point X = "-2.138" Y = "-3.024" Z = "-0.672" T = "1325480660528" alpha = "-15.47" beta = "24.29" gamma = "-128.03" />
			<Point X = "-2.036" Y = "2.96" Z = "1.312" T = "1325480660570" alpha = "-69.72" beta = "37.8" gamma = "-172.9" />
			<Point X = "-1.037" Y = "10.543" Z = "2.424" T = "1325480660609" alpha = "-12.74" beta = "11.55" gamma = "-93.24" />
			<Point X = "-0.181" Y = "10.833" Z = "0.767" T = "1325480660653" alpha = "23.73" beta = "-32.06" gamma = "42.49" />
			<Point X = "0.941" Y = "3.242" Z = "-0.747" T = "1325480660691" alpha = "15.96" beta = "-38.15" gamma = "129.22" />
			<Point X = "0.795" Y = "-2.587" Z = "-0.355" T = "1325480660733" alpha = "35.84" beta = "-9.52" gamma = "145.53" />
			<Point X = "0.224" Y = "-6.997" Z = "0.162" T = "1325480660770" alpha = "20.23" beta = "0.21" gamma = "113.96" />
			<Point X = "-0.052" Y = "-9.171" Z = "-1.026" T = "1325480660819" alpha = "17.01" beta = "-12.04" gamma = "38.43" />
			<Point X = "-0.136" Y = "-6.447" Z = "-1.217" T = "1325480660851" alpha = "-10.08" beta = "-7.35" gamma = "-57.12" />
			<Point X = "-0.539" Y = "-0.456" Z = "-0.677" T = "1325480660891" alpha = "-51.52" beta = "17.5" gamma = "-150.36" />
			<Point X = "-0.644" Y = "5.368" Z = "2.123" T = "1325480660934" alpha = "-27.02" beta = "29.89" gamma = "-150.01" />
			<Point X = "0.195" Y = "10.267" Z = "1.572" T = "1325480660970" alpha = "-4.55" beta = "-3.57" gamma = "-51.03" />
			<Point X = "0.076" Y = "7.251" Z = "0.111" T = "1325480661009" alpha = "6.79" beta = "-35.56" gamma = "74.9" />
			<Point X = "0.401" Y = "0.776" Z = "-0.847" T = "1325480661049" alpha = "44.59" beta = "-27.3" gamma = "121.8" />
			<Point X = "0.748" Y = "-3.12" Z = "-0.251" T = "1325480661090" alpha = "41.44" beta = "0.49" gamma = "121.31" />
			<Point X = "0.579" Y = "-7.906" Z = "-0.199" T = "1325480661129" alpha = "27.65" beta = "5.6" gamma = "91.56" />
			<Point X = "0.293" Y = "-8.022" Z = "-1.059" T = "1325480661170" alpha = "15.19" beta = "-9.38" gamma = "37.24" />
			<Point X = "0.761" Y = "-4.946" Z = "-1.419" T = "1325480661215" alpha = "-2.45" beta = "-7.21" gamma = "-44.87" />
			<Point X = "0.205" Y = "-1.459" Z = "-1.206" T = "1325480661252" alpha = "-33.04" beta = "14.7" gamma = "-113.96" />
			<Point X = "-0.872" Y = "1.737" Z = "-0.002" T = "1325480661294" alpha = "-50.05" beta = "44.94" gamma = "-166.39" />
			<Point X = "-1.544" Y = "5.62" Z = "1.868" T = "1325480661330" alpha = "-23.73" beta = "43.12" gamma = "-155.68" />
			<Point X = "-1.059" Y = "7.869" Z = "2.126" T = "1325480661371" alpha = "-24.78" beta = "18.9" gamma = "-83.37" />
			<Point X = "-0.267" Y = "6.854" Z = "1.412" T = "1325480661412" alpha = "-4.76" beta = "-12.81" gamma = "14.98" />
			<Point X = "-0.024" Y = "3.133" Z = "0.77" T = "1325480661451" alpha = "19.53" beta = "-21.63" gamma = "71.47" />
			<Point X = "-0.161" Y = "0.322" Z = "0.084" T = "1325480661488" alpha = "36.47" beta = "-18.69" gamma = "101.43" />
			<Point X = "-0.048" Y = "-1.772" Z = "-0.054" T = "1325480661534" alpha = "33.53" beta = "-14.63" gamma = "101.92" />
			<Point X = "0.549" Y = "-3.45" Z = "-0.824" T = "1325480661570" alpha = "27.44" beta = "-12.81" gamma = "92.12" />
		</Stroke>
	</Gesture>
</Gestures>
